README.rst
setup.cfg
setup.py
stash/__init__.py
stash/main.py
stash.py.egg-info/PKG-INFO
stash.py.egg-info/SOURCES.txt
stash.py.egg-info/dependency_links.txt
stash.py.egg-info/top_level.txt
stash/algorithms/__init__.py
stash/algorithms/lru.py
stash/algorithms/core/__init__.py
stash/algorithms/core/base.py
stash/algorithms/core/prime_context.py
stash/archives/__init__.py
stash/archives/a_apsw.py
stash/archives/a_memory.py
stash/archives/a_sqlite.py
stash/archives/core/__init__.py
stash/archives/core/base.py
stash/caches/__init__.py
stash/caches/c_memory.py
stash/caches/core/__init__.py
stash/caches/core/base.py
stash/core/__init__.py
stash/core/helpers.py
stash/core/modules/__init__.py
stash/core/modules/base.py
stash/core/modules/manager.py
stash/lib/__init__.py
stash/lib/six.py
stash/serializers/__init__.py
stash/serializers/s_jsonpickle.py
stash/serializers/s_msgpack.py
stash/serializers/s_none.py
stash/serializers/s_pickle.py
stash/serializers/core/__init__.py
stash/serializers/core/base.py