Metadata-Version: 1.1
Name: stash.py
Version: 1.2.0
Summary: Dictionary-style storage interface with a modular interface for algorithms, archives, caches and serializers
Home-page: https://github.com/fuzeman/stash.py
Author: Dean Gardiner
Author-email: me@dgardiner.net
License: MIT
Platform: any
Classifier: Development Status :: 4 - Beta
Classifier: Intended Audience :: Developers
Classifier: License :: OSI Approved :: MIT License
Classifier: Operating System :: OS Independent
Classifier: Programming Language :: Python
Classifier: Programming Language :: Python :: 2
Classifier: Programming Language :: Python :: 3
Classifier: Topic :: Database :: Front-Ends
